senlinclient/__init__.py
senlinclient/client.py
senlinclient/plugin.py
senlinclient/common/__init__.py
senlinclient/common/exc.py
senlinclient/common/format_utils.py
senlinclient/common/i18n.py
senlinclient/common/utils.py
senlinclient/locale/zh_CN/LC_MESSAGES/senlinclient.po
senlinclient/tests/__init__.py
senlinclient/tests/functional/__init__.py
senlinclient/tests/functional/base.py
senlinclient/tests/functional/test_actions.py
senlinclient/tests/functional/test_cluster_policy.py
senlinclient/tests/functional/test_clusters.py
senlinclient/tests/functional/test_events.py
senlinclient/tests/functional/test_help.py
senlinclient/tests/functional/test_nodes.py
senlinclient/tests/functional/test_policies.py
senlinclient/tests/functional/test_policy_types.py
senlinclient/tests/functional/test_profile_types.py
senlinclient/tests/functional/test_profiles.py
senlinclient/tests/functional/test_readonly_senlin.py
senlinclient/tests/functional/test_receivers.py
senlinclient/tests/functional/test_version.py
senlinclient/tests/functional/policies/deletion_policy.yaml
senlinclient/tests/functional/profiles/cirros_basic.yaml
senlinclient/tests/test_specs/deletion_policy.yaml
senlinclient/tests/test_specs/nova_server.yaml
senlinclient/tests/unit/__init__.py
senlinclient/tests/unit/fakes.py
senlinclient/tests/unit/test_format_utils.py
senlinclient/tests/unit/test_plugin.py
senlinclient/tests/unit/test_utils.py
senlinclient/tests/unit/v1/__init__.py
senlinclient/tests/unit/v1/fakes.py
senlinclient/tests/unit/v1/test_action.py
senlinclient/tests/unit/v1/test_build_info.py
senlinclient/tests/unit/v1/test_client.py
senlinclient/tests/unit/v1/test_cluster.py
senlinclient/tests/unit/v1/test_cluster_policy.py
senlinclient/tests/unit/v1/test_event.py
senlinclient/tests/unit/v1/test_node.py
senlinclient/tests/unit/v1/test_policy.py
senlinclient/tests/unit/v1/test_policy_type.py
senlinclient/tests/unit/v1/test_profile.py
senlinclient/tests/unit/v1/test_profile_type.py
python_senlinclient-3.1.0.dist-info/AUTHORS
python_senlinclient-3.1.0.dist-info/LICENSE
python_senlinclient-3.1.0.dist-info/METADATA
python_senlinclient-3.1.0.dist-info/WHEEL
python_senlinclient-3.1.0.dist-info/entry_points.txt
python_senlinclient-3.1.0.dist-info/pbr.json
python_senlinclient-3.1.0.dist-info/top_level.txt
python_senlinclient-3.1.0.dist-info/RECORD
